fzfaws/__init__.py
fzfaws/__main__.py
fzfaws/cli.py
fzfaws/fzfaws.yml
fzfaws/cloudformation/__init__.py
fzfaws/cloudformation/changeset_stack.py
fzfaws/cloudformation/cloudformation.py
fzfaws/cloudformation/create_stack.py
fzfaws/cloudformation/delete_stack.py
fzfaws/cloudformation/drift_stack.py
fzfaws/cloudformation/ls_stack.py
fzfaws/cloudformation/main.py
fzfaws/cloudformation/update_stack.py
fzfaws/cloudformation/validate_stack.py
fzfaws/cloudformation/helper/__init__.py
fzfaws/cloudformation/helper/cloudformationargs.py
fzfaws/cloudformation/helper/file_validation.py
fzfaws/cloudformation/helper/paramprocessor.py
fzfaws/cloudwatch/__init__.py
fzfaws/cloudwatch/cloudwatch.py
fzfaws/ec2/__init__.py
fzfaws/ec2/ec2.py
fzfaws/ec2/ls_instance.py
fzfaws/ec2/main.py
fzfaws/ec2/reboot_instance.py
fzfaws/ec2/ssh_instance.py
fzfaws/ec2/start_instance.py
fzfaws/ec2/stop_instance.py
fzfaws/ec2/terminate_instance.py
fzfaws/iam/__init__.py
fzfaws/iam/iam.py
fzfaws/kms/__init__.py
fzfaws/kms/kms.py
fzfaws/libs/fzf-0.21.1-darwin_386
fzfaws/libs/fzf-0.21.1-darwin_amd64
fzfaws/libs/fzf-0.21.1-linux_386
fzfaws/libs/fzf-0.21.1-linux_amd64
fzfaws/route53/__init__.py
fzfaws/route53/route53.py
fzfaws/s3/__init__.py
fzfaws/s3/bucket_s3.py
fzfaws/s3/delete_s3.py
fzfaws/s3/download_s3.py
fzfaws/s3/ls_s3.py
fzfaws/s3/main.py
fzfaws/s3/object_s3.py
fzfaws/s3/presign_s3.py
fzfaws/s3/s3.py
fzfaws/s3/upload_s3.py
fzfaws/s3/helper/__init__.py
fzfaws/s3/helper/exclude_file.py
fzfaws/s3/helper/get_copy_args.py
fzfaws/s3/helper/s3args.py
fzfaws/s3/helper/s3progress.py
fzfaws/s3/helper/s3transferwrapper.py
fzfaws/s3/helper/sync_s3.py
fzfaws/s3/helper/walk_s3_folder.py
fzfaws/sns/__init__.py
fzfaws/sns/sns.py
fzfaws/utils/__init__.py
fzfaws/utils/exceptions.py
fzfaws/utils/fileloader.py
fzfaws/utils/pyfzf.py
fzfaws/utils/session.py
fzfaws/utils/spinner.py
fzfaws/utils/util.py
fzfaws-0.1.1.dist-info/LICENSE
fzfaws-0.1.1.dist-info/METADATA
fzfaws-0.1.1.dist-info/WHEEL
fzfaws-0.1.1.dist-info/entry_points.txt
fzfaws-0.1.1.dist-info/top_level.txt
fzfaws-0.1.1.dist-info/RECORD
